<HRSC_Image>
  <Img_ID>100001213</Img_ID>
  <Place_ID>100000006</Place_ID>
  <Source_ID>100000001</Source_ID>
  <Img_NO>100001213</Img_NO>
  <Img_FileName>100001213</Img_FileName>
  <Img_FileFmt>bmp</Img_FileFmt>
  <Img_Date>2014-07-01</Img_Date>
  <Img_CusType>sealand</Img_CusType>
  <Img_Des>
  </Img_Des>
  <Img_Location>32.6623,117.121053</Img_Location>
  <Img_SizeWidth>1187</Img_SizeWidth>
  <Img_SizeHeight>839</Img_SizeHeight>
  <Img_SizeDepth>3</Img_SizeDepth>
  <Img_Resolution>1.07</Img_Resolution>
  <Img_Resolution_Layer>18</Img_Resolution_Layer>
  <Img_Scale>115</Img_Scale>
  <Img_SclPxlNum>
  </Img_SclPxlNum>
  <segmented>0</segmented>
  <Img_Havemask>0</Img_Havemask>
  <Img_MaskFileName>
  </Img_MaskFileName>
  <Img_MaskFileFmt>
  </Img_MaskFileFmt>
  <Img_MaskType>
  </Img_MaskType>
  <Img_SegFileName>
  </Img_SegFileName>
  <Img_SegFileFmt>
  </Img_SegFileFmt>
  <Img_Rotation>288d</Img_Rotation>
  <Annotated>1</Annotated>
  <HRSC_Objects>
    <HRSC_Object>
      <Object_ID>100001420</Object_ID>
      <Class_ID>100000025</Class_ID>
      <Object_NO>100001420</Object_NO>
      <truncated>1</truncated>
      <difficult>0</difficult>
      <box_xmin>59</box_xmin>
      <box_ymin>15</box_ymin>
      <box_xmax>284</box_xmax>
      <box_ymax>478</box_ymax>
      <mbox_cx>161.667</mbox_cx>
      <mbox_cy>247.8404</mbox_cy>
      <mbox_w>486.5218</mbox_w>
      <mbox_h>70.76003</mbox_h>
      <mbox_ang>-1.216997</mbox_ang>
      <segmented>0</segmented>
      <seg_color>
      </seg_color>
      <header_x>78</header_x>
      <header_y>474</header_y>
    </HRSC_Object>
    <HRSC_Object>
      <Object_ID>100001421</Object_ID>
      <Class_ID>100000001</Class_ID>
      <Object_NO>100001421</Object_NO>
      <truncated>0</truncated>
      <difficult>0</difficult>
      <box_xmin>86</box_xmin>
      <box_ymin>579</box_ymin>
      <box_xmax>297</box_xmax>
      <box_ymax>680</box_ymax>
      <mbox_cx>193.9958</mbox_cx>
      <mbox_cy>631.5107</mbox_cy>
      <mbox_w>222.0872</mbox_w>
      <mbox_h>35.12341</mbox_h>
      <mbox_ang>0.3762867</mbox_ang>
      <segmented>0</segmented>
      <seg_color>
      </seg_color>
      <header_x>292</header_x>
      <header_y>673</header_y>
    </HRSC_Object>
    <HRSC_Object>
      <Object_ID>100001422</Object_ID>
      <Class_ID>100000010</Class_ID>
      <Object_NO>100001422</Object_NO>
      <truncated>0</truncated>
      <difficult>0</difficult>
      <box_xmin>429</box_xmin>
      <box_ymin>27</box_ymin>
      <box_xmax>603</box_xmax>
      <box_ymax>406</box_ymax>
      <mbox_cx>523.5978</mbox_cx>
      <mbox_cy>211.7233</mbox_cy>
      <mbox_w>397.529</mbox_w>
      <mbox_h>69.05192</mbox_h>
      <mbox_ang>-1.213262</mbox_ang>
      <segmented>0</segmented>
      <seg_color>
      </seg_color>
      <header_x>590</header_x>
      <header_y>32</header_y>
    </HRSC_Object>
    <HRSC_Object>
      <Object_ID>100001423</Object_ID>
      <Class_ID>100000010</Class_ID>
      <Object_NO>100001423</Object_NO>
      <truncated>0</truncated>
      <difficult>0</difficult>
      <box_xmin>531</box_xmin>
      <box_ymin>61</box_ymin>
      <box_xmax>702</box_xmax>
      <box_ymax>444</box_ymax>
      <mbox_cx>626.4386</mbox_cx>
      <mbox_cy>248.0613</mbox_cy>
      <mbox_w>399.6228</mbox_w>
      <mbox_h>71.11994</mbox_h>
      <mbox_ang>-1.228383</mbox_ang>
      <segmented>0</segmented>
      <seg_color>
      </seg_color>
      <header_x>690</header_x>
      <header_y>63</header_y>
    </HRSC_Object>
    <HRSC_Object>
      <Object_ID>100001424</Object_ID>
      <Class_ID>100000001</Class_ID>
      <Object_NO>100001424</Object_NO>
      <truncated>0</truncated>
      <difficult>0</difficult>
      <box_xmin>362</box_xmin>
      <box_ymin>441</box_ymin>
      <box_xmax>464</box_xmax>
      <box_ymax>655</box_ymax>
      <mbox_cx>418.6947</mbox_cx>
      <mbox_cy>545.4332</mbox_cy>
      <mbox_w>229.0601</mbox_w>
      <mbox_h>40.2356</mbox_h>
      <mbox_ang>-1.199304</mbox_ang>
      <segmented>0</segmented>
      <seg_color>
      </seg_color>
      <header_x>456</header_x>
      <header_y>444</header_y>
    </HRSC_Object>
    <HRSC_Object>
      <Object_ID>100001425</Object_ID>
      <Class_ID>100000007</Class_ID>
      <Object_NO>100001425</Object_NO>
      <truncated>0</truncated>
      <difficult>0</difficult>
      <box_xmin>904</box_xmin>
      <box_ymin>174</box_ymin>
      <box_xmax>1028</box_xmax>
      <box_ymax>464</box_ymax>
      <mbox_cx>962.5</mbox_cx>
      <mbox_cy>321.5</mbox_cy>
      <mbox_w>303.3884</mbox_w>
      <mbox_h>46.47336</mbox_h>
      <mbox_ang>-1.225139</mbox_ang>
      <segmented>0</segmented>
      <seg_color>
      </seg_color>
      <header_x>912</header_x>
      <header_y>456</header_y>
    </HRSC_Object>
    <HRSC_Object>
      <Object_ID>100001426</Object_ID>
      <Class_ID>100000007</Class_ID>
      <Object_NO>100001426</Object_NO>
      <truncated>0</truncated>
      <difficult>0</difficult>
      <box_xmin>988</box_xmin>
      <box_ymin>193</box_ymin>
      <box_xmax>1106</box_xmax>
      <box_ymax>465</box_ymax>
      <mbox_cx>1051.801</mbox_cx>
      <mbox_cy>324.6075</mbox_cy>
      <mbox_w>287.8315</mbox_w>
      <mbox_h>43.90555</mbox_h>
      <mbox_ang>-1.218114</mbox_ang>
      <segmented>0</segmented>
      <seg_color>
      </seg_color>
      <header_x>1100</header_x>
      <header_y>196</header_y>
    </HRSC_Object>
    <HRSC_Object>
      <Object_ID>100001427</Object_ID>
      <Class_ID>100000007</Class_ID>
      <Object_NO>100001427</Object_NO>
      <truncated>0</truncated>
      <difficult>0</difficult>
      <box_xmin>777</box_xmin>
      <box_ymin>533</box_ymin>
      <box_xmax>896</box_xmax>
      <box_ymax>821</box_ymax>
      <mbox_cx>830.5</mbox_cx>
      <mbox_cy>679.5</mbox_cy>
      <mbox_w>304.7128</mbox_w>
      <mbox_h>45.7535</mbox_h>
      <mbox_ang>-1.208984</mbox_ang>
      <segmented>0</segmented>
      <seg_color>
      </seg_color>
      <header_x>781</header_x>
      <header_y>818</header_y>
    </HRSC_Object>
    <HRSC_Object>
      <Object_ID>100001428</Object_ID>
      <Class_ID>100000007</Class_ID>
      <Object_NO>100001428</Object_NO>
      <truncated>0</truncated>
      <difficult>0</difficult>
      <box_xmin>856</box_xmin>
      <box_ymin>551</box_ymin>
      <box_xmax>971</box_xmax>
      <box_ymax>827</box_ymax>
      <mbox_cx>921</mbox_cx>
      <mbox_cy>688</mbox_cy>
      <mbox_w>289.0238</mbox_w>
      <mbox_h>43.14225</mbox_h>
      <mbox_ang>-1.21583</mbox_ang>
      <segmented>0</segmented>
      <seg_color>
      </seg_color>
      <header_x>967</header_x>
      <header_y>556</header_y>
    </HRSC_Object>
  </HRSC_Objects>
</HRSC_Image>