<HRSC_Image>
  <Img_ID>100001598</Img_ID>
  <Place_ID>100000006</Place_ID>
  <Source_ID>100000001</Source_ID>
  <Img_NO>100001598</Img_NO>
  <Img_FileName>100001598</Img_FileName>
  <Img_FileFmt>bmp</Img_FileFmt>
  <Img_Date>2006-01-01</Img_Date>
  <Img_CusType>sealand</Img_CusType>
  <Img_Des>
  </Img_Des>
  <Img_Location>32.6623,117.121053</Img_Location>
  <Img_SizeWidth>907</Img_SizeWidth>
  <Img_SizeHeight>717</Img_SizeHeight>
  <Img_SizeDepth>3</Img_SizeDepth>
  <Img_Resolution>1.07</Img_Resolution>
  <Img_Resolution_Layer>18</Img_Resolution_Layer>
  <Img_Scale>106</Img_Scale>
  <Img_SclPxlNum>
  </Img_SclPxlNum>
  <segmented>0</segmented>
  <Img_Havemask>0</Img_Havemask>
  <Img_MaskFileName>
  </Img_MaskFileName>
  <Img_MaskFileFmt>
  </Img_MaskFileFmt>
  <Img_MaskType>
  </Img_MaskType>
  <Img_SegFileName>
  </Img_SegFileName>
  <Img_SegFileFmt>
  </Img_SegFileFmt>
  <Img_Rotation>292d</Img_Rotation>
  <Annotated>1</Annotated>
  <HRSC_Objects>
    <HRSC_Object>
      <Object_ID>100002624</Object_ID>
      <Class_ID>100000027</Class_ID>
      <Object_NO>100002624</Object_NO>
      <truncated>0</truncated>
      <difficult>0</difficult>
      <box_xmin>123</box_xmin>
      <box_ymin>261</box_ymin>
      <box_xmax>227</box_xmax>
      <box_ymax>504</box_ymax>
      <mbox_cx>175.2571</mbox_cx>
      <mbox_cy>383.6566</mbox_cy>
      <mbox_w>263.928</mbox_w>
      <mbox_h>28.09579</mbox_h>
      <mbox_ang>-1.211143</mbox_ang>
      <segmented>0</segmented>
      <seg_color>
      </seg_color>
      <header_x>209</header_x>
      <header_y>292</header_y>
    </HRSC_Object>
    <HRSC_Object>
      <Object_ID>100002625</Object_ID>
      <Class_ID>100000027</Class_ID>
      <Object_NO>100002625</Object_NO>
      <truncated>0</truncated>
      <difficult>0</difficult>
      <box_xmin>219</box_xmin>
      <box_ymin>303</box_ymin>
      <box_xmax>309</box_xmax>
      <box_ymax>518</box_ymax>
      <mbox_cx>264.5775</mbox_cx>
      <mbox_cy>409.4132</mbox_cy>
      <mbox_w>230.2303</mbox_w>
      <mbox_h>27.8317</mbox_h>
      <mbox_ang>-1.214785</mbox_ang>
      <segmented>0</segmented>
      <seg_color>
      </seg_color>
      <header_x>300</header_x>
      <header_y>317</header_y>
    </HRSC_Object>
  </HRSC_Objects>
</HRSC_Image>