<HRSC_Image>
  <Img_ID>100001606</Img_ID>
  <Place_ID>100000006</Place_ID>
  <Source_ID>100000001</Source_ID>
  <Img_NO>100001606</Img_NO>
  <Img_FileName>100001606</Img_FileName>
  <Img_FileFmt>bmp</Img_FileFmt>
  <Img_Date>2002-12-01</Img_Date>
  <Img_CusType>sealand</Img_CusType>
  <Img_Des>
  </Img_Des>
  <Img_Location>32.6623,117.121053</Img_Location>
  <Img_SizeWidth>950</Img_SizeWidth>
  <Img_SizeHeight>803</Img_SizeHeight>
  <Img_SizeDepth>3</Img_SizeDepth>
  <Img_Resolution>1.07</Img_Resolution>
  <Img_Resolution_Layer>18</Img_Resolution_Layer>
  <Img_Scale>127</Img_Scale>
  <Img_SclPxlNum>
  </Img_SclPxlNum>
  <segmented>0</segmented>
  <Img_Havemask>0</Img_Havemask>
  <Img_MaskFileName>
  </Img_MaskFileName>
  <Img_MaskFileFmt>
  </Img_MaskFileFmt>
  <Img_MaskType>
  </Img_MaskType>
  <Img_SegFileName>
  </Img_SegFileName>
  <Img_SegFileFmt>
  </Img_SegFileFmt>
  <Img_Rotation>319d</Img_Rotation>
  <Annotated>1</Annotated>
  <HRSC_Objects>
    <HRSC_Object>
      <Object_ID>100002668</Object_ID>
      <Class_ID>100000025</Class_ID>
      <Object_NO>100002668</Object_NO>
      <truncated>0</truncated>
      <difficult>0</difficult>
      <box_xmin>170</box_xmin>
      <box_ymin>67</box_ymin>
      <box_xmax>426</box_xmax>
      <box_ymax>528</box_ymax>
      <mbox_cx>286.0585</mbox_cx>
      <mbox_cy>290.2535</mbox_cy>
      <mbox_w>497.7834</mbox_w>
      <mbox_h>70.642</mbox_h>
      <mbox_ang>1.124097</mbox_ang>
      <segmented>0</segmented>
      <seg_color>
      </seg_color>
      <header_x>179</header_x>
      <header_y>72</header_y>
    </HRSC_Object>
    <HRSC_Object>
      <Object_ID>100002669</Object_ID>
      <Class_ID>100000025</Class_ID>
      <Object_NO>100002669</Object_NO>
      <truncated>0</truncated>
      <difficult>0</difficult>
      <box_xmin>527</box_xmin>
      <box_ymin>269</box_ymin>
      <box_xmax>724</box_xmax>
      <box_ymax>755</box_ymax>
      <mbox_cx>633.941</mbox_cx>
      <mbox_cy>506.084</mbox_cy>
      <mbox_w>494.7696</mbox_w>
      <mbox_h>76.59332</mbox_h>
      <mbox_ang>-1.261434</mbox_ang>
      <segmented>0</segmented>
      <seg_color>
      </seg_color>
      <header_x>705</header_x>
      <header_y>272</header_y>
    </HRSC_Object>
  </HRSC_Objects>
</HRSC_Image>