<HRSC_Image>
  <Img_ID>100001240</Img_ID>
  <Place_ID>100000006</Place_ID>
  <Source_ID>100000001</Source_ID>
  <Img_NO>100001240</Img_NO>
  <Img_FileName>100001240</Img_FileName>
  <Img_FileFmt>bmp</Img_FileFmt>
  <Img_Date>2014-01-01</Img_Date>
  <Img_CusType>sealand</Img_CusType>
  <Img_Des>
  </Img_Des>
  <Img_Location>32.6623,117.121053</Img_Location>
  <Img_SizeWidth>1095</Img_SizeWidth>
  <Img_SizeHeight>799</Img_SizeHeight>
  <Img_SizeDepth>3</Img_SizeDepth>
  <Img_Resolution>1.07</Img_Resolution>
  <Img_Resolution_Layer>18</Img_Resolution_Layer>
  <Img_Scale>140</Img_Scale>
  <Img_SclPxlNum>
  </Img_SclPxlNum>
  <segmented>0</segmented>
  <Img_Havemask>0</Img_Havemask>
  <Img_MaskFileName>
  </Img_MaskFileName>
  <Img_MaskFileFmt>
  </Img_MaskFileFmt>
  <Img_MaskType>
  </Img_MaskType>
  <Img_SegFileName>
  </Img_SegFileName>
  <Img_SegFileFmt>
  </Img_SegFileFmt>
  <Img_Rotation>043d</Img_Rotation>
  <Annotated>1</Annotated>
  <HRSC_Objects>
    <HRSC_Object>
      <Object_ID>100001525</Object_ID>
      <Class_ID>100000011</Class_ID>
      <Object_NO>100001525</Object_NO>
      <truncated>0</truncated>
      <difficult>1</difficult>
      <box_xmin>366</box_xmin>
      <box_ymin>216</box_ymin>
      <box_xmax>746</box_xmax>
      <box_ymax>287</box_ymax>
      <mbox_cx>556.014</mbox_cx>
      <mbox_cy>253.4036</mbox_cy>
      <mbox_w>382.8176</mbox_w>
      <mbox_h>37.92554</mbox_h>
      <mbox_ang>-0.1343103</mbox_ang>
      <segmented>1</segmented>
      <seg_color>
      </seg_color>
      <header_x>367</header_x>
      <header_y>282</header_y>
    </HRSC_Object>
    <HRSC_Object>
      <Object_ID>100001526</Object_ID>
      <Class_ID>100000001</Class_ID>
      <Object_NO>100001526</Object_NO>
      <truncated>0</truncated>
      <difficult>1</difficult>
      <box_xmin>503</box_xmin>
      <box_ymin>363</box_ymin>
      <box_xmax>746</box_xmax>
      <box_ymax>426</box_ymax>
      <mbox_cx>622.3384</mbox_cx>
      <mbox_cy>396.616</mbox_cy>
      <mbox_w>248.2093</mbox_w>
      <mbox_h>37.80675</mbox_h>
      <mbox_ang>-0.1807026</mbox_ang>
      <segmented>1</segmented>
      <seg_color>
      </seg_color>
      <header_x>503</header_x>
      <header_y>419</header_y>
    </HRSC_Object>
    <HRSC_Object>
      <Object_ID>100001527</Object_ID>
      <Class_ID>100000001</Class_ID>
      <Object_NO>100001527</Object_NO>
      <truncated>0</truncated>
      <difficult>0</difficult>
      <box_xmin>506</box_xmin>
      <box_ymin>489</box_ymin>
      <box_xmax>757</box_xmax>
      <box_ymax>557</box_ymax>
      <mbox_cx>630.0585</mbox_cx>
      <mbox_cy>525.7116</mbox_cy>
      <mbox_w>255.1691</mbox_w>
      <mbox_h>38.61386</mbox_h>
      <mbox_ang>-0.1906056</mbox_ang>
      <segmented>0</segmented>
      <seg_color>
      </seg_color>
      <header_x>506</header_x>
      <header_y>547</header_y>
    </HRSC_Object>
    <HRSC_Object>
      <Object_ID>100001528</Object_ID>
      <Class_ID>100000001</Class_ID>
      <Object_NO>100001528</Object_NO>
      <truncated>0</truncated>
      <difficult>0</difficult>
      <box_xmin>728</box_xmin>
      <box_ymin>532</box_ymin>
      <box_xmax>863</box_xmax>
      <box_ymax>583</box_ymax>
      <mbox_cx>794.2847</mbox_cx>
      <mbox_cy>559.3502</mbox_cy>
      <mbox_w>132.9974</mbox_w>
      <mbox_h>33.35225</mbox_h>
      <mbox_ang>-0.1886145</mbox_ang>
      <segmented>0</segmented>
      <seg_color>
      </seg_color>
      <header_x>729</header_x>
      <header_y>572</header_y>
    </HRSC_Object>
    <HRSC_Object>
      <Object_ID>100001529</Object_ID>
      <Class_ID>100000003</Class_ID>
      <Object_NO>100001529</Object_NO>
      <truncated>0</truncated>
      <difficult>0</difficult>
      <box_xmin>444</box_xmin>
      <box_ymin>564</box_ymin>
      <box_xmax>725</box_xmax>
      <box_ymax>637</box_ymax>
      <mbox_cx>583.5065</mbox_cx>
      <mbox_cy>603.6067</mbox_cy>
      <mbox_w>283.6338</mbox_w>
      <mbox_h>37.88219</mbox_h>
      <mbox_ang>-0.1918126</mbox_ang>
      <segmented>0</segmented>
      <seg_color>
      </seg_color>
      <header_x>445</header_x>
      <header_y>631</header_y>
    </HRSC_Object>
    <HRSC_Object>
      <Object_ID>100001530</Object_ID>
      <Class_ID>100000001</Class_ID>
      <Object_NO>100001530</Object_NO>
      <truncated>0</truncated>
      <difficult>0</difficult>
      <box_xmin>628</box_xmin>
      <box_ymin>414</box_ymin>
      <box_xmax>764</box_xmax>
      <box_ymax>462</box_ymax>
      <mbox_cx>694.4663</mbox_cx>
      <mbox_cy>439.545</mbox_cy>
      <mbox_w>133.8377</mbox_w>
      <mbox_h>31.63687</mbox_h>
      <mbox_ang>-0.2036576</mbox_ang>
      <segmented>0</segmented>
      <seg_color>
      </seg_color>
      <header_x>629</header_x>
      <header_y>452</header_y>
    </HRSC_Object>
    <HRSC_Object>
      <Object_ID>100001531</Object_ID>
      <Class_ID>100000001</Class_ID>
      <Object_NO>100001531</Object_NO>
      <truncated>0</truncated>
      <difficult>0</difficult>
      <box_xmin>576</box_xmin>
      <box_ymin>470</box_ymin>
      <box_xmax>712</box_xmax>
      <box_ymax>514</box_ymax>
      <mbox_cx>645.2185</mbox_cx>
      <mbox_cy>490.957</mbox_cy>
      <mbox_w>137.2947</mbox_w>
      <mbox_h>30.05145</mbox_h>
      <mbox_ang>-0.1804096</mbox_ang>
      <segmented>0</segmented>
      <seg_color>
      </seg_color>
      <header_x>710</header_x>
      <header_y>479</header_y>
    </HRSC_Object>
  </HRSC_Objects>
</HRSC_Image>