<HRSC_Image>
  <Img_ID>100001089</Img_ID>
  <Place_ID>100000005</Place_ID>
  <Source_ID>100000001</Source_ID>
  <Img_NO>100001089</Img_NO>
  <Img_FileName>100001089</Img_FileName>
  <Img_FileFmt>bmp</Img_FileFmt>
  <Img_Date>2006-07-01</Img_Date>
  <Img_CusType>sealand</Img_CusType>
  <Img_Des>
  </Img_Des>
  <Img_Location>36.960756,76.328608</Img_Location>
  <Img_SizeWidth>1072</Img_SizeWidth>
  <Img_SizeHeight>810</Img_SizeHeight>
  <Img_SizeDepth>3</Img_SizeDepth>
  <Img_Resolution>1.07</Img_Resolution>
  <Img_Resolution_Layer>18</Img_Resolution_Layer>
  <Img_Scale>134</Img_Scale>
  <Img_SclPxlNum>
  </Img_SclPxlNum>
  <segmented>0</segmented>
  <Img_Havemask>0</Img_Havemask>
  <Img_MaskFileName>
  </Img_MaskFileName>
  <Img_MaskFileFmt>
  </Img_MaskFileFmt>
  <Img_MaskType>
  </Img_MaskType>
  <Img_SegFileName>
  </Img_SegFileName>
  <Img_SegFileFmt>
  </Img_SegFileFmt>
  <Img_Rotation>002d</Img_Rotation>
  <Annotated>1</Annotated>
  <HRSC_Objects>
    <HRSC_Object>
      <Object_ID>100001035</Object_ID>
      <Class_ID>100000025</Class_ID>
      <Object_NO>100001035</Object_NO>
      <truncated>0</truncated>
      <difficult>0</difficult>
      <box_xmin>355</box_xmin>
      <box_ymin>130</box_ymin>
      <box_xmax>895</box_xmax>
      <box_ymax>240</box_ymax>
      <mbox_cx>625.9385</mbox_cx>
      <mbox_cy>179.2894</mbox_cy>
      <mbox_w>547.5804</mbox_w>
      <mbox_h>72.6218</mbox_h>
      <mbox_ang>0.1018246</mbox_ang>
      <segmented>0</segmented>
      <seg_color>
      </seg_color>
      <header_x>358</header_x>
      <header_y>153</header_y>
    </HRSC_Object>
    <HRSC_Object>
      <Object_ID>100001036</Object_ID>
      <Class_ID>100000025</Class_ID>
      <Object_NO>100001036</Object_NO>
      <truncated>0</truncated>
      <difficult>0</difficult>
      <box_xmin>348</box_xmin>
      <box_ymin>194</box_ymin>
      <box_xmax>890</box_xmax>
      <box_ymax>308</box_ymax>
      <mbox_cx>616.9051</mbox_cx>
      <mbox_cy>249.908</mbox_cy>
      <mbox_w>546.4585</mbox_w>
      <mbox_h>74.17849</mbox_h>
      <mbox_ang>0.1040938</mbox_ang>
      <segmented>0</segmented>
      <seg_color>
      </seg_color>
      <header_x>350</header_x>
      <header_y>214</header_y>
    </HRSC_Object>
    <HRSC_Object>
      <Object_ID>100001037</Object_ID>
      <Class_ID>100000025</Class_ID>
      <Object_NO>100001037</Object_NO>
      <truncated>0</truncated>
      <difficult>0</difficult>
      <box_xmin>328</box_xmin>
      <box_ymin>294</box_ymin>
      <box_xmax>875</box_xmax>
      <box_ymax>413</box_ymax>
      <mbox_cx>600.0602</mbox_cx>
      <mbox_cy>348.4484</mbox_cy>
      <mbox_w>549.5034</mbox_w>
      <mbox_h>75.24729</mbox_h>
      <mbox_ang>0.1085461</mbox_ang>
      <segmented>0</segmented>
      <seg_color>
      </seg_color>
      <header_x>330</header_x>
      <header_y>315</header_y>
    </HRSC_Object>
    <HRSC_Object>
      <Object_ID>100001038</Object_ID>
      <Class_ID>100000025</Class_ID>
      <Object_NO>100001038</Object_NO>
      <truncated>0</truncated>
      <difficult>0</difficult>
      <box_xmin>336</box_xmin>
      <box_ymin>490</box_ymin>
      <box_xmax>788</box_xmax>
      <box_ymax>596</box_ymax>
      <mbox_cx>561.2671</mbox_cx>
      <mbox_cy>547.5287</mbox_cy>
      <mbox_w>459.162</mbox_w>
      <mbox_h>73.22184</mbox_h>
      <mbox_ang>0.1076428</mbox_ang>
      <segmented>0</segmented>
      <seg_color>
      </seg_color>
      <header_x>784</header_x>
      <header_y>572</header_y>
    </HRSC_Object>
    <HRSC_Object>
      <Object_ID>100001039</Object_ID>
      <Class_ID>100000025</Class_ID>
      <Object_NO>100001039</Object_NO>
      <truncated>0</truncated>
      <difficult>0</difficult>
      <box_xmin>648</box_xmin>
      <box_ymin>637</box_ymin>
      <box_xmax>846</box_xmax>
      <box_ymax>697</box_ymax>
      <mbox_cx>746.0682</mbox_cx>
      <mbox_cy>666.9189</mbox_cy>
      <mbox_w>201.5507</mbox_w>
      <mbox_h>45.04279</mbox_h>
      <mbox_ang>0.1168557</mbox_ang>
      <segmented>0</segmented>
      <seg_color>
      </seg_color>
      <header_x>844</header_x>
      <header_y>681</header_y>
    </HRSC_Object>
  </HRSC_Objects>
</HRSC_Image>