<HRSC_Image>
  <Img_ID>100001407</Img_ID>
  <Place_ID>100000006</Place_ID>
  <Source_ID>100000001</Source_ID>
  <Img_NO>100001407</Img_NO>
  <Img_FileName>100001407</Img_FileName>
  <Img_FileFmt>bmp</Img_FileFmt>
  <Img_Date>2007-05-01</Img_Date>
  <Img_CusType>sealand</Img_CusType>
  <Img_Des>
  </Img_Des>
  <Img_Location>32.6623,117.121053</Img_Location>
  <Img_SizeWidth>1125</Img_SizeWidth>
  <Img_SizeHeight>796</Img_SizeHeight>
  <Img_SizeDepth>3</Img_SizeDepth>
  <Img_Resolution>1.07</Img_Resolution>
  <Img_Resolution_Layer>18</Img_Resolution_Layer>
  <Img_Scale>131</Img_Scale>
  <Img_SclPxlNum>
  </Img_SclPxlNum>
  <segmented>0</segmented>
  <Img_Havemask>0</Img_Havemask>
  <Img_MaskFileName>
  </Img_MaskFileName>
  <Img_MaskFileFmt>
  </Img_MaskFileFmt>
  <Img_MaskType>
  </Img_MaskType>
  <Img_SegFileName>
  </Img_SegFileName>
  <Img_SegFileFmt>
  </Img_SegFileFmt>
  <Img_Rotation>263d</Img_Rotation>
  <Annotated>1</Annotated>
  <HRSC_Objects>
    <HRSC_Object>
      <Object_ID>100002050</Object_ID>
      <Class_ID>100000016</Class_ID>
      <Object_NO>100002050</Object_NO>
      <truncated>0</truncated>
      <difficult>0</difficult>
      <box_xmin>493</box_xmin>
      <box_ymin>112</box_ymin>
      <box_xmax>1001</box_xmax>
      <box_ymax>240</box_ymax>
      <mbox_cx>748.0776</mbox_cx>
      <mbox_cy>169.6457</mbox_cy>
      <mbox_w>505.6423</mbox_w>
      <mbox_h>100.1367</mbox_h>
      <mbox_ang>0.09057183</mbox_ang>
      <segmented>0</segmented>
      <seg_color>
      </seg_color>
      <header_x>994</header_x>
      <header_y>207</header_y>
    </HRSC_Object>
    <HRSC_Object>
      <Object_ID>100002051</Object_ID>
      <Class_ID>100000001</Class_ID>
      <Object_NO>100002051</Object_NO>
      <truncated>0</truncated>
      <difficult>0</difficult>
      <box_xmin>228</box_xmin>
      <box_ymin>249</box_ymin>
      <box_xmax>387</box_xmax>
      <box_ymax>296</box_ymax>
      <mbox_cx>307.3907</mbox_cx>
      <mbox_cy>271.895</mbox_cy>
      <mbox_w>160.7572</mbox_w>
      <mbox_h>37.30048</mbox_h>
      <mbox_ang>0.09983676</mbox_ang>
      <segmented>0</segmented>
      <seg_color>
      </seg_color>
      <header_x>229</header_x>
      <header_y>264</header_y>
    </HRSC_Object>
    <HRSC_Object>
      <Object_ID>100002052</Object_ID>
      <Class_ID>100000015</Class_ID>
      <Object_NO>100002052</Object_NO>
      <truncated>0</truncated>
      <difficult>0</difficult>
      <box_xmin>136</box_xmin>
      <box_ymin>533</box_ymin>
      <box_xmax>471</box_xmax>
      <box_ymax>614</box_ymax>
      <mbox_cx>302.757</mbox_cx>
      <mbox_cy>576.0807</mbox_cy>
      <mbox_w>340.3781</mbox_w>
      <mbox_h>61.65335</mbox_h>
      <mbox_ang>0.1058028</mbox_ang>
      <segmented>0</segmented>
      <seg_color>
      </seg_color>
      <header_x>468</header_x>
      <header_y>598</header_y>
    </HRSC_Object>
    <HRSC_Object>
      <Object_ID>100002053</Object_ID>
      <Class_ID>100000001</Class_ID>
      <Object_NO>100002053</Object_NO>
      <truncated>0</truncated>
      <difficult>0</difficult>
      <box_xmin>458</box_xmin>
      <box_ymin>645</box_ymin>
      <box_xmax>617</box_xmax>
      <box_ymax>687</box_ymax>
      <mbox_cx>537.2795</mbox_cx>
      <mbox_cy>664.6766</mbox_cy>
      <mbox_w>162.4357</mbox_w>
      <mbox_h>33.39873</mbox_h>
      <mbox_ang>0.08390107</mbox_ang>
      <segmented>0</segmented>
      <seg_color>
      </seg_color>
      <header_x>457</header_x>
      <header_y>658</header_y>
    </HRSC_Object>
    <HRSC_Object>
      <Object_ID>100002054</Object_ID>
      <Class_ID>100000001</Class_ID>
      <Object_NO>100002054</Object_NO>
      <truncated>0</truncated>
      <difficult>0</difficult>
      <box_xmin>456</box_xmin>
      <box_ymin>676</box_ymin>
      <box_xmax>617</box_xmax>
      <box_ymax>721</box_ymax>
      <mbox_cx>534.2928</mbox_cx>
      <mbox_cy>697.9751</mbox_cy>
      <mbox_w>162.5887</mbox_w>
      <mbox_h>34.58296</mbox_h>
      <mbox_ang>0.07266554</mbox_ang>
      <segmented>0</segmented>
      <seg_color>
      </seg_color>
      <header_x>456</header_x>
      <header_y>693</header_y>
    </HRSC_Object>
  </HRSC_Objects>
</HRSC_Image>